py_nullable/__init__.py
py_nullable/__version__.py
py_nullable/decorator.py
py_nullable/exception.py
py_nullable/nullable.py
py_nullable/py.typed
py_nullable-0.3.2.dist-info/LICENSE
py_nullable-0.3.2.dist-info/METADATA
py_nullable-0.3.2.dist-info/WHEEL
py_nullable-0.3.2.dist-info/top_level.txt
py_nullable-0.3.2.dist-info/RECORD
