Metadata-Version: 2.1
Name: py-nullable
Version: 0.3.2
Summary: Python's None Wrapper, inspired by java.util.Optional
Author: miyamo2theppl
License: MIT License
Project-URL: repository, https://github.com/miyamo2theppl/py_nullable.git
Keywords: None,null,nullable,Java,Null Safety
Classifier: Programming Language :: Python :: 3.7
Classifier: Programming Language :: Python :: 3.8
Classifier: Programming Language :: Python :: 3.9
Classifier: Programming Language :: Python :: 3.10
Classifier: Programming Language :: Python :: 3.11
Requires-Python: <3.12,>=3.7
License-File: LICENSE
Requires-Dist: typing-extensions
